protein_quest/__init__.py
protein_quest/__version__.py
protein_quest/cli.py
protein_quest/converter.py
protein_quest/emdb.py
protein_quest/filters.py
protein_quest/go.py
protein_quest/io.py
protein_quest/mcp_server.py
protein_quest/parallel.py
protein_quest/py.typed
protein_quest/ss.py
protein_quest/structure.py
protein_quest/taxonomy.py
protein_quest/uniprot.py
protein_quest/utils.py
protein_quest/alphafold/__init__.py
protein_quest/alphafold/confidence.py
protein_quest/alphafold/entry_summary.py
protein_quest/alphafold/fetch.py
protein_quest/pdbe/__init__.py
protein_quest/pdbe/fetch.py
protein_quest-1.0.0.dist-info/METADATA
protein_quest-1.0.0.dist-info/WHEEL
protein_quest-1.0.0.dist-info/entry_points.txt
protein_quest-1.0.0.dist-info/licenses/LICENSE
protein_quest-1.0.0.dist-info/RECORD
