Metadata-Version: 2.4
Name: protein_quest
Version: 1.0.0
Summary: Search/retrieve/filter proteins and protein structures
Project-URL: Homepage, https://github.com/haddocking/protein-quest
Project-URL: Issues, https://github.com/haddocking/protein-quest/issues
Project-URL: Documentation, https://www.bonvinlab.org/protein-quest/
Project-URL: Source, https://github.com/haddocking/protein-quest
License-File: LICENSE
Keywords: alphafold,mmcif,pdb,protein,protein structure,uniprot
Classifier: Development Status :: 5 - Production/Stable
Classifier: Environment :: Console
Classifier: Framework :: AsyncIO
Classifier: Intended Audience :: Science/Research
Classifier: License :: OSI Approved :: Apache Software License
Classifier: Natural Language :: English
Classifier: Operating System :: MacOS
Classifier: Operating System :: POSIX
Classifier: Operating System :: POSIX :: Linux
Classifier: Programming Language :: Python :: 3.13
Classifier: Programming Language :: Python :: 3.14
Classifier: Topic :: Scientific/Engineering :: Bio-Informatics
Classifier: Topic :: Scientific/Engineering :: Chemistry
Classifier: Typing :: Typed
Requires-Python: >=3.13
Requires-Dist: aiofiles>=24.1.0
Requires-Dist: aiohttp-retry>=2.9.1
Requires-Dist: aiohttp[speedups]>=3.11.18
Requires-Dist: attrs>=25.3.0
Requires-Dist: cattrs[orjson]>=24.1.3
Requires-Dist: dask>=2025.5.1
Requires-Dist: distributed>=2025.5.1
Requires-Dist: gemmi>=0.7.3
Requires-Dist: mmcif>=0.92.0
Requires-Dist: platformdirs>=4.3.8
Requires-Dist: psutil>=7.0.0
Requires-Dist: rich-argparse>=1.7.1
Requires-Dist: rich>=14.0.0
Requires-Dist: shtab>=1.7.2
Requires-Dist: sparqlwrapper>=2.0.0
Requires-Dist: tqdm>=4.67.1
Requires-Dist: yarl>=1.20.1
Provides-Extra: mcp
Requires-Dist: fastmcp>=2.11.3; extra == 'mcp'
Requires-Dist: pydantic>=2.12.0; extra == 'mcp'
